cpp/parser.cpp
cpp/argparse.cpp
cpp/c_str_parsing.cpp
cpp/extractor.cpp
cpp/implementation.cpp
cpp/fastnumbers.cpp
fastnumbers-5.1.1.dist-info/top_level.txt
fastnumbers-5.1.1.dist-info/RECORD
fastnumbers-5.1.1.dist-info/LICENSE
fastnumbers-5.1.1.dist-info/METADATA
fastnumbers-5.1.1.dist-info/WHEEL
fastnumbers/fastnumbers.pyi
fastnumbers/fastnumbers.cpython-38-i386-linux-gnu.so
fastnumbers/__init__.py
fastnumbers/_version.py
fastnumbers/py.typed
