Metadata-Version: 2.1
Name: fastnumbers
Version: 5.1.1
Summary: Super-fast and clean conversions to numbers.
Author-email: "Seth M. Morton" <drtuba78@gmail.com>
License: MIT
Project-URL: Homepage, https://github.com/SethMMorton/fastnumbers
Project-URL: Documentation, https://fastnumbers.readthedocs.io/
Project-URL: Issues, https://github.com/SethMMorton/fastnumbers/issues
Project-URL: Changelog, https://github.com/SethMMorton/fastnumbers/blob/main/CHANGELOG.md
Keywords: conversion,numeric,performance
Classifier: Development Status :: 5 - Production/Stable
Classifier: Intended Audience :: Science/Research
Classifier: Intended Audience :: Developers
Classifier: Intended Audience :: Information Technology
Classifier: Intended Audience :: System Administrators
Classifier: Intended Audience :: Financial and Insurance Industry
Classifier: Operating System :: OS Independent
Classifier: License :: OSI Approved :: MIT License
Classifier: Natural Language :: English
Classifier: Programming Language :: Python :: 3
Classifier: Programming Language :: Python :: 3.8
Classifier: Programming Language :: Python :: 3.9
Classifier: Programming Language :: Python :: 3.10
Classifier: Programming Language :: Python :: 3.11
Classifier: Programming Language :: Python :: 3.12
Classifier: Programming Language :: Python :: 3.13
Classifier: Topic :: Scientific/Engineering :: Information Analysis
Classifier: Topic :: Utilities
Classifier: Topic :: Text Processing
Classifier: Topic :: Text Processing :: Filters
Requires-Python: >=3.8
License-File: LICENSE
Provides-Extra: fast
Requires-Dist: fastnumbers >=2.0.0 ; extra == 'fast'
Provides-Extra: icu
Requires-Dist: PyICU >=1.0.0 ; extra == 'icu'
